<ui:UiBinder xmlns:ui='urn:ui:com.google.gwt.uibinder'
             xmlns:g='urn:import:com.google.gwt.user.client.ui'
             xmlns:boot='urn:import:com.github.gwtbootstrap.client.ui'>

    <ui:style>
        .row {
            margin-bottom: 10px;
        }

        .label {
            display: inline-block;
            width: 120px;
            text-align: right;
            margin-right: 5px;
        }

        .inline {
            display: inline-block;
        }
    </ui:style>

    <g:HTMLPanel>
        <div>
            <g:Label text="N° Dossier" styleName="{style.label}"/>
            <g:SuggestBox ui:field="numDossier" width="168px"/>

            <g:Label text="Nom ou prénom" styleName="{style.label}"/>
            <boot:TextBox ui:field="firstnameOrlastname" width="168px"/>
        </div>

        <div class="{style.row}">
            <g:Label text="Formation" styleName="{style.label}"/>
            <boot:ValueListBox ui:field="filiere" width="180px"/>

            <g:Label text="Niveau demandé" styleName="{style.label}"/>
            <boot:ValueListBox ui:field="niveauEtude" width="180px"/>
        </div>

        <div class="{style.row}">
            <g:Label text="Statut dossier" styleName="{style.label}"/>
            <boot:ValueListBox ui:field="status" width="180px"/>

            <g:Label text="Fratrie au GSR" styleName="{style.label}"/>
            <boot:CheckBox ui:field="gsrFraterie" styleName="{style.inline}"/>

            <g:Label text="Parents au GSR" styleName="{style.label}"/>
            <boot:CheckBox ui:field="parentGsr" styleName="{style.inline}"/>
        </div>
    </g:HTMLPanel>
</ui:UiBinder>
