<ui:UiBinder xmlns:ui='urn:ui:com.google.gwt.uibinder'
             xmlns:g='urn:import:com.google.gwt.user.client.ui'
             xmlns:boot='urn:import:com.github.gwtbootstrap.client.ui'>
    <g:HTMLPanel>
        <boot:Form type="HORIZONTAL">
            <boot:ControlGroup>
                <boot:ControlLabel>N° Dossier</boot:ControlLabel>
                <boot:Controls>
                    <boot:TextBox ui:field="numDossier" width="250px"/>
                </boot:Controls>
            </boot:ControlGroup>

            <boot:ControlGroup>
                <boot:ControlLabel>Nom ou prénom</boot:ControlLabel>
                <boot:Controls>
                    <boot:TextBox ui:field="firstnameOrlastname" width="250px"/>
                </boot:Controls>
            </boot:ControlGroup>

            <boot:ControlGroup>
                <boot:ControlLabel>Filière</boot:ControlLabel>
                <boot:Controls>
                    <boot:ValueListBox ui:field="filiere" width="250px"/>
                </boot:Controls>
            </boot:ControlGroup>

            <boot:ControlGroup>
                <boot:ControlLabel>Niveau d'études</boot:ControlLabel>
                <boot:Controls>
                    <boot:ValueListBox ui:field="niveauEtude" width="250px"/>
                </boot:Controls>
            </boot:ControlGroup>

        </boot:Form>
    </g:HTMLPanel>
</ui:UiBinder>
